{
  "_type": "request",
  "url": "{{ base_url }}/rest/api/3/groupuserpicker",
  "method": "GET",
  "body": {
    "mimeType": "No Body"
  },
  "headers": [],
  "parameters": [
    {
      "name": "query",
      "value": "string",
      "disabled": false
    },
    {
      "name": "maxResults",
      "value": "50",
      "disabled": true
    },
    {
      "name": "showAvatar",
      "value": "true",
      "disabled": true
    },
    {
      "name": "fieldId",
      "value": "string",
      "disabled": true
    },
    {
      "name": "projectId",
      "value": "string",
      "disabled": true
    },
    {
      "name": "issueTypeId",
      "value": "string",
      "disabled": true
    },
    {
      "name": "avatarSize",
      "value": "xsmall",
      "disabled": true
    },
    {
      "name": "caseInsensitive",
      "value": "true",
      "disabled": true
    },
    {
      "name": "excludeConnectAddons",
      "value": "true",
      "disabled": true
    }
  ],
  "pathParameters": [],
  "authentication": {
    "type": "basic",
    "username": "{{ httpUsername }}",
    "password": "{{ httpPassword }}"
  },
  "sortOrder": 0
}
