{
  "_type": "request",
  "url": "{{ base_url }}/radar/bgp/routes/pfx2as",
  "method": "GET",
  "body": {
    "mimeType": "No Body"
  },
  "headers": [
    {
      "name": "X-Auth-Email",
      "value": "{{ xAuthEmail }}",
      "disabled": false
    },
    {
      "name": "X-Auth-Key",
      "value": "{{ xAuthKey }}",
      "disabled": false
    }
  ],
  "parameters": [
    {
      "name": "prefix",
      "value": "1.1.1.0/24",
      "disabled": true
    },
    {
      "name": "origin",
      "value": "0",
      "disabled": true
    },
    {
      "name": "rpkiStatus",
      "value": "INVALID",
      "disabled": true
    },
    {
      "name": "longestPrefixMatch",
      "value": "true",
      "disabled": true
    },
    {
      "name": "format",
      "value": "json",
      "disabled": true
    }
  ],
  "pathParameters": [],
  "authentication": {
    "type": "bearer",
    "token": "{{bearerToken}}",
    "prefix": ""
  },
  "sortOrder": 5
}
