{
  "_type": "request",
  "url": "{{ base_url }}/users",
  "method": "POST",
  "body": {
    "mimeType": "application/json",
    "text": "{\n  \"user\": null\n}"
  },
  "headers": [
    {
      "name": "Accept",
      "value": "application/vnd.pagerduty+json;version=2",
      "disabled": false
    },
    {
      "name": "Content-Type",
      "value": "application/json",
      "disabled": false
    },
    {
      "name": "From",
      "value": "user@example.com",
      "disabled": false
    },
    {
      "name": "Authorization",
      "value": "{{ authorization }}",
      "disabled": false
    }
  ],
  "parameters": [],
  "pathParameters": [],
  "authentication": {
    "type": "No Auth"
  },
  "sortOrder": 1
}
