{
  "_type": "request",
  "url": "{{ base_url }}/rest/api/3/comment/{commentId}/properties/{propertyKey}",
  "method": "PUT",
  "body": {
    "mimeType": "application/json",
    "text": "null"
  },
  "headers": [],
  "parameters": [],
  "pathParameters": [
    {
      "name": "commentId",
      "value": ""
    },
    {
      "name": "propertyKey",
      "value": ""
    }
  ],
  "authentication": {
    "type": "basic",
    "username": "{{ httpUsername }}",
    "password": "{{ httpPassword }}"
  },
  "sortOrder": 3
}
