{
  "_type": "request",
  "url": "{{ base_url }}/rest/api/3/project/{projectKeyOrId}/permissionscheme",
  "method": "PUT",
  "body": {
    "mimeType": "application/json",
    "text": "{\n  \"id\": 0\n}"
  },
  "headers": [],
  "parameters": [
    {
      "name": "expand",
      "value": "string",
      "disabled": true
    }
  ],
  "pathParameters": [
    {
      "name": "projectKeyOrId",
      "value": ""
    }
  ],
  "authentication": {
    "type": "basic",
    "username": "{{ httpUsername }}",
    "password": "{{ httpPassword }}"
  },
  "sortOrder": 2
}
